{
  "@context": {
    "foaf": "http://xmlns.com/foaf/0.1/",
    "schema": "http://schema.org/",
    "owl": "http://www.w3.org/2002/07/owl#",
    "rdfs": "http://www.w3.org/2000/01/rdf-schema#",
    "dc": "http://purl.org/dc/terms/",
    "xsd": "http://www.w3.org/2001/XMLSchema#",
    "rdf": "http://www.w3.org/1999/02/22-rdf-syntax-ns#",
    "skos": "http://www.w3.org/2004/02/skos/core#"
  },
  "@graph": [
    {
      "@id": "_:g47250428301280",
      "foaf:firstName": "An",
      "foaf:lastName": "Heirman",
      "schema:affiliation": {
        "@id": "_:g47250429926200"
      },
      "@type": "foaf:person",
      "foaf:mbox": {
        "@id": "mailto:an@gim.be"
      }
    },
    {
      "@id": "_:g47250429926200",
      "foaf:name": "G.I.M. - Geographic Information Management"
    },
    {
      "@id": "https://data.vlaanderen.be/ns/openbaardomein/begraafplaats#BegraafplaatsRij",
      "rdfs:comment": {
        "@value": "Een rij is een verzameling graven van hetzelfde type. Een rij ligt typisch volledig binnen een bepaald blok. ",
        "@language": "nl"
      },
      "rdfs:isDefinedBy": {
        "@id": "https://data.vlaanderen.be/ns/openbaardomein/begraafplaats"
      },
      "@type": "owl:Class",
      "rdfs:label": {
        "@value": "Begraafplaats rij",
        "@language": "nl"
      },
      "rdfs:subClassOf": {
        "@id": "https://data.vlaanderen.be/ns/openbaardomein/terreindeel#Terreindeel"
      }
    },
    {
      "@id": "https://data.vlaanderen.be/ns/openbaardomein/begraafplaats",
      "dc:mediator": {
        "@id": "_:g47250426759180"
      },
      "dc:title": {
        "@value": "Vocabularium begraafplaats",
        "@language": "nl"
      },
      "dc:issued": {
        "@value": "2018-06-08",
        "@type": "xsd:date"
      },
      "http://www.w3.org/2001/02pd/rec54#editor": {
        "@id": "_:g47250426590000"
      },
      "dc:contributor": [
        {
          "@id": "_:g47250428301280"
        },
        {
          "@id": "_:g47250427517780"
        },
        {
          "@id": "_:g47250422984980"
        },
        {
          "@id": "_:g47250427533560"
        },
        {
          "@id": "_:g47250428215520"
        },
        {
          "@id": "_:g47250427491680"
        },
        {
          "@id": "_:g47250430726000"
        },
        {
          "@id": "_:g47250423003460"
        },
        {
          "@id": "_:g47250422217120"
        },
        {
          "@id": "_:g47250423547960"
        },
        {
          "@id": "_:g47250426585660"
        },
        {
          "@id": "_:g47250427393020"
        },
        {
          "@id": "_:g47250429989920"
        },
        {
          "@id": "_:g47250430448460"
        },
        {
          "@id": "_:g47250427511400"
        },
        {
          "@id": "_:g47250428603400"
        },
        {
          "@id": "_:g47250428283500"
        },
        {
          "@id": "_:g47250430240320"
        },
        {
          "@id": "_:g47250430640700"
        },
        {
          "@id": "_:g47250430588200"
        },
        {
          "@id": "_:g47250430119120"
        },
        {
          "@id": "_:g47250423712840"
        },
        {
          "@id": "_:g47250423869940"
        },
        {
          "@id": "_:g47250428040380"
        },
        {
          "@id": "_:g47250426733600"
        },
        {
          "@id": "_:g47250427493580"
        },
        {
          "@id": "_:g47250428133060"
        },
        {
          "@id": "_:g47250427501260"
        },
        {
          "@id": "_:g47250430065060"
        }
      ],
      "foaf:maker": {
        "@id": "_:g47250431015120"
      },
      "http://purl.org/vocab/vann/preferredNamespacePrefix": "odb",
      "@type": "owl:Ontology",
      "rdfs:label": {
        "@value": "Vocabularium begraafplaats",
        "@language": "nl"
      },
      "http://purl.org/vocab/vann/preferredNamespaceUri": "https://data.vlaanderen.be/ns/openbaardomein/begraafplaats",
      "dc:license": {
        "@id": "https://overheid.vlaanderen.be/sites/default/files/documenten/ict-egov/licenties/hergebruik/modellicentie_gratis_hergebruik_v1_0.html"
      }
    },
    {
      "@id": "https://data.vlaanderen.be/ns/openbaardomein/infrastructuur#capaciteit",
      "@type": "rdf:Property",
      "rdfs:label": {
        "@value": "capaciteit",
        "@language": "nl"
      }
    },
    {
      "@id": "https://data.vlaanderen.be/ns/openbaardomein/begraafplaats#grafteken",
      "rdfs:comment": {
        "@value": "Duidt aan of er al dan niet een grafteken, bijvoorbeeld een zerk, aanwezig is.",
        "@language": "nl"
      },
      "rdfs:isDefinedBy": {
        "@id": "https://data.vlaanderen.be/ns/openbaardomein/begraafplaats"
      },
      "rdfs:range": {
        "@id": "xsd:boolean"
      },
      "rdfs:domain": {
        "@id": "https://data.vlaanderen.be/ns/openbaardomein/begraafplaats#Graf"
      },
      "@type": "owl:DatatypeProperty",
      "rdfs:label": {
        "@value": "grafteken",
        "@language": "nl"
      }
    },
    {
      "@id": "https://data.vlaanderen.be/ns/openbaardomein/begraafplaats#Graf",
      "http://purl.org/vocab/vann/usageNote": {
        "@value": "Naar GRB-skeletoptie groen- en begraafplaatsenbeheer: BPG1 Grafrand (afgeleid)",
        "@language": "nl"
      },
      "rdfs:comment": {
        "@value": "Plaats waar iemand begraven ligt.",
        "@language": "nl"
      },
      "rdfs:isDefinedBy": {
        "@id": "https://data.vlaanderen.be/ns/openbaardomein/begraafplaats"
      },
      "@type": "owl:Class",
      "rdfs:label": {
        "@value": "Graf",
        "@language": "nl"
      },
      "rdfs:subClassOf": {
        "@id": "https://data.vlaanderen.be/ns/openbaardomein#Element"
      }
    },
    {
      "@id": "_:g47250428215520",
      "foaf:firstName": "Emmanuel",
      "foaf:lastName": "Ampe",
      "schema:affiliation": {
        "@id": "_:g47250428064860"
      },
      "@type": "foaf:person",
      "foaf:mbox": {
        "@id": "mailto:emmanuel@vvog.info"
      }
    },
    {
      "@id": "_:g47250428064860",
      "foaf:name": "Vereniging voor Openbaar Groen"
    },
    {
      "@id": "https://data.vlaanderen.be/ns/openbaardomein/begraafplaats#graftype",
      "rdfs:comment": {
        "@value": "Het type graf.",
        "@language": "nl"
      },
      "rdfs:isDefinedBy": {
        "@id": "https://data.vlaanderen.be/ns/openbaardomein/begraafplaats"
      },
      "rdfs:range": {
        "@id": "skos:Concept"
      },
      "rdfs:domain": {
        "@id": "https://data.vlaanderen.be/ns/openbaardomein/begraafplaats#Graf"
      },
      "@type": "owl:ObjectProperty",
      "rdfs:label": {
        "@value": "graftype",
        "@language": "nl"
      }
    },
    {
      "@id": "_:g47250427431040",
      "foaf:name": "Stad Lier"
    },
    {
      "@id": "_:g47250423003460",
      "foaf:firstName": "Pieter",
      "foaf:lastName": "Deckers",
      "schema:affiliation": {
        "@id": "_:g47250422968060"
      },
      "@type": "foaf:person",
      "foaf:mbox": {
        "@id": "mailto:pieter.deckers@oost-vlaanderen.be"
      }
    },
    {
      "@id": "_:g47250422968060",
      "foaf:name": "Provincie Oost-Vlaanderen"
    },
    {
      "@id": "_:g47250427444440",
      "foaf:name": "Hogeschool Gent"
    },
    {
      "@id": "_:g47250422217120",
      "foaf:firstName": "Tom",
      "foaf:lastName": "Van Herck",
      "schema:affiliation": {
        "@id": "_:g47250421739200"
      },
      "@type": "foaf:person",
      "foaf:mbox": {
        "@id": "mailto:Tom.vanherck@kb.vlaanderen.be"
      }
    },
    {
      "@id": "_:g47250421739200",
      "foaf:name": "Informatie Vlaanderen"
    },
    {
      "@id": "https://data.vlaanderen.be/ns/openbaardomein/begraafplaats#bezetting",
      "rdfs:comment": {
        "@value": "Geeft de bezetting van een object weer op een bepaald tijdstip, bijvoorbeeld het aantal ingenomen parkeerplaatsen van een parking.",
        "@language": "nl"
      },
      "rdfs:isDefinedBy": {
        "@id": "https://data.vlaanderen.be/ns/openbaardomein/begraafplaats"
      },
      "rdfs:range": {
        "@id": "xsd:integer"
      },
      "rdfs:domain": {
        "@id": "schema:Thing"
      },
      "@type": "owl:DatatypeProperty",
      "rdfs:label": {
        "@value": "bezetting",
        "@language": "nl"
      }
    },
    {
      "@id": "_:g47250426585660",
      "foaf:firstName": "Liesbet",
      "foaf:lastName": "DHondt",
      "schema:affiliation": {
        "@id": "_:g47250426456340"
      },
      "@type": "foaf:person",
      "foaf:mbox": {
        "@id": "mailto:liesbet.dhondt@bosa.fgov.be"
      }
    },
    {
      "@id": "_:g47250426456340",
      "foaf:name": "Federale Overheidsdienst Beleid en Ondersteuning"
    },
    {
      "@id": "_:g47250428357160",
      "foaf:name": "Provincie Vlaams-Brabant"
    },
    {
      "@id": "_:g47250427608260",
      "foaf:name": "Stad Sint-Niklaas"
    },
    {
      "@id": "https://data.vlaanderen.be/ns/openbaardomein/begraafplaats#BegraafplaatsBlok",
      "rdfs:comment": {
        "@value": "Een deel binnen de begraafplaats. Dit blok is op zichzelf staande structuur binnen de begraafplaats en zorgt voor een gebiedsdekkende structuur.",
        "@language": "nl"
      },
      "rdfs:isDefinedBy": {
        "@id": "https://data.vlaanderen.be/ns/openbaardomein/begraafplaats"
      },
      "@type": "owl:Class",
      "rdfs:label": {
        "@value": "Begraafplaats blok",
        "@language": "nl"
      },
      "rdfs:subClassOf": {
        "@id": "https://data.vlaanderen.be/ns/openbaardomein/terreindeel#Terreindeel"
      }
    },
    {
      "@id": "_:g47250428283500",
      "foaf:firstName": "Bea",
      "foaf:lastName": "Toppet",
      "schema:affiliation": {
        "@id": "_:g47250428173860"
      },
      "@type": "foaf:person",
      "foaf:mbox": {
        "@id": "mailto:bea.toppet@pxl.be"
      }
    },
    {
      "@id": "_:g47250428173860",
      "foaf:name": "Hogeschool PXL"
    },
    {
      "@id": "https://data.vlaanderen.be/ns/openbaardomein/begraafplaats#Urnenveld",
      "http://purl.org/vocab/vann/usageNote": {
        "@value": "Naar GRB-skeletoptie groen- en begraafplaatsenbeheer - BPU2: Urnenveld",
        "@language": "nl"
      },
      "rdfs:comment": {
        "@value": "Een urnenveld is een constructie in of op de grond met nissen waarin urnen geplaatst worden.",
        "@language": "nl"
      },
      "rdfs:isDefinedBy": {
        "@id": "https://data.vlaanderen.be/ns/openbaardomein/begraafplaats"
      },
      "@type": "owl:Class",
      "rdfs:label": {
        "@value": "Urnenveld",
        "@language": "nl"
      },
      "rdfs:subClassOf": {
        "@id": "https://data.vlaanderen.be/ns/openbaardomein#Element"
      }
    },
    {
      "@id": "_:g47250430240320",
      "foaf:firstName": "Joris",
      "foaf:lastName": "Verbeken",
      "schema:affiliation": {
        "@id": "_:g47250430256260"
      },
      "@type": "foaf:person",
      "foaf:mbox": {
        "@id": "mailto:joris.verbeken@aalst.be"
      }
    },
    {
      "@id": "_:g47250430256260",
      "foaf:name": "Stad Aalst"
    },
    {
      "@id": "_:g47250430336740",
      "foaf:name": "Stad Oostende"
    },
    {
      "@id": "_:g47250430588200",
      "foaf:firstName": "Ruben",
      "foaf:lastName": "Deblauwe",
      "schema:affiliation": {
        "@id": "_:g47250430603180"
      },
      "@type": "foaf:person",
      "foaf:mbox": {
        "@id": "mailto:ruben.deblauwe@elia.be"
      }
    },
    {
      "@id": "_:g47250430603180",
      "foaf:name": "Elia"
    },
    {
      "@id": "https://data.vlaanderen.be/ns/openbaardomein/begraafplaats#Columbarium",
      "http://purl.org/vocab/vann/usageNote": {
        "@value": "Naar GRB-skeletoptie groen- en begraafplaatsenbeheer - BPU1: Columbarium",
        "@language": "nl"
      },
      "rdfs:comment": {
        "@value": "Een columbarium is een muur met nissen waarin urnen geplaatst worden.",
        "@language": "nl"
      },
      "rdfs:isDefinedBy": {
        "@id": "https://data.vlaanderen.be/ns/openbaardomein/begraafplaats"
      },
      "@type": "owl:Class",
      "rdfs:label": {
        "@value": "Columbarium",
        "@language": "nl"
      },
      "rdfs:subClassOf": {
        "@id": "https://data.vlaanderen.be/ns/openbaardomein#Element"
      }
    },
    {
      "@id": "https://data.vlaanderen.be/ns/openbaardomein/begraafplaats#grafkelderAanwezig",
      "rdfs:comment": {
        "@value": "Duidt aan of het graf voorzien is van een ondergrondse of bovengrondse ruimte.",
        "@language": "nl"
      },
      "rdfs:isDefinedBy": {
        "@id": "https://data.vlaanderen.be/ns/openbaardomein/begraafplaats"
      },
      "rdfs:range": {
        "@id": "xsd:boolean"
      },
      "rdfs:domain": {
        "@id": "https://data.vlaanderen.be/ns/openbaardomein/begraafplaats#Graf"
      },
      "@type": "owl:DatatypeProperty",
      "rdfs:label": {
        "@value": "grafkelder aanwezig",
        "@language": "nl"
      }
    },
    {
      "@id": "_:g47250423712840",
      "foaf:firstName": "Luk",
      "foaf:lastName": "Mutsaerts",
      "schema:affiliation": {
        "@id": "_:g47250424321840"
      },
      "@type": "foaf:person",
      "foaf:mbox": {
        "@id": "mailto:luk.mutsaerts@vlaanderen.be"
      }
    },
    {
      "@id": "_:g47250424321840",
      "foaf:name": "Departement Omgeving"
    },
    {
      "@id": "_:g47250427415680",
      "foaf:name": "Provincie Oost-Vlaanderen"
    },
    {
      "@id": "_:g47250430465260",
      "foaf:name": "Stad Aalst"
    },
    {
      "@id": "_:g47250423869940",
      "foaf:firstName": "Joke",
      "foaf:lastName": "Van De Maele",
      "schema:affiliation": {
        "@id": "_:g47250423967220"
      },
      "@type": "foaf:person",
      "foaf:mbox": {
        "@id": "mailto:joke.vandemaele@stad.antwerpen.be"
      }
    },
    {
      "@id": "_:g47250423967220",
      "foaf:name": "Stad Antwerpen"
    },
    {
      "@id": "_:g47250427517780",
      "foaf:firstName": "Kristien",
      "foaf:lastName": "De Rouck",
      "schema:affiliation": {
        "@id": "_:g47250427444440"
      },
      "@type": "foaf:person",
      "foaf:mbox": {
        "@id": "mailto:kristien.derouck@hogent.be"
      }
    },
    {
      "@id": "_:g47250428040380",
      "foaf:firstName": "Wouter",
      "foaf:lastName": "Verhelst",
      "schema:affiliation": {
        "@id": "_:g47250430204900"
      },
      "@type": "foaf:person",
      "foaf:mbox": {
        "@id": "mailto:w.verhelst@wvi.be"
      }
    },
    {
      "@id": "_:g47250430204900",
      "foaf:name": "WVI"
    },
    {
      "@id": "_:g47250427139520",
      "foaf:name": "Geosparc"
    },
    {
      "@id": "_:g47250428455280",
      "foaf:name": "Stad Gent - Data & Informatie"
    },
    {
      "@id": "_:g47250422984980",
      "foaf:firstName": "Oliver",
      "foaf:lastName": "May",
      "schema:affiliation": {
        "@id": "_:g47250427139520"
      },
      "@type": "foaf:person",
      "foaf:mbox": {
        "@id": "mailto:oliver.may@geosparc.com"
      }
    },
    {
      "@id": "_:g47250427533560",
      "foaf:firstName": "Berdien",
      "foaf:lastName": "De Roo",
      "schema:affiliation": {
        "@id": "_:g47250427967660"
      },
      "@type": "foaf:person",
      "foaf:mbox": {
        "@id": "mailto:berdien.deroo@geosparc.com"
      }
    },
    {
      "@id": "_:g47250427967660",
      "foaf:name": "Geosparc"
    },
    {
      "@id": "_:g47250426733600",
      "foaf:firstName": "Filip",
      "foaf:lastName": "Mahieu",
      "schema:affiliation": {
        "@id": "_:g47250426589080"
      },
      "@type": "foaf:person",
      "foaf:mbox": {
        "@id": "mailto:filip.mahieu@oost-vlaanderen.be"
      }
    },
    {
      "@id": "_:g47250426589080",
      "foaf:name": "Provincie Oost-Vlaanderen"
    },
    {
      "@id": "_:g47250427493580",
      "foaf:firstName": "Dennis",
      "foaf:lastName": "Devriendt",
      "schema:affiliation": {
        "@id": "_:g47250427346220"
      },
      "@type": "foaf:person",
      "foaf:mbox": {
        "@id": "mailto:dennis.devriendt@hogent.be"
      }
    },
    {
      "@id": "_:g47250427346220",
      "foaf:name": "Hogeschool Gent"
    },
    {
      "@id": "_:g47250430127380",
      "foaf:name": "Gemeente Evergem"
    },
    {
      "@id": "_:g47250427491680",
      "foaf:firstName": "Steven",
      "foaf:lastName": "De Vriendt",
      "schema:affiliation": {
        "@id": "_:g47250427415680"
      },
      "@type": "foaf:person",
      "foaf:mbox": {
        "@id": "mailto:steven.de.vriendt@oost-vlaanderen.be"
      }
    },
    {
      "@id": "_:g47250430726000",
      "foaf:firstName": "Nicolas",
      "foaf:lastName": "De Blieck",
      "schema:affiliation": {
        "@id": "_:g47250430743000"
      },
      "@type": "foaf:person",
      "foaf:mbox": {
        "@id": "mailto:nicolas.deblieck@farys.be"
      }
    },
    {
      "@id": "_:g47250430743000",
      "foaf:name": "TMVW"
    },
    {
      "@id": "_:g47250426759180",
      "foaf:mbox": {
        "@id": "mailto:oslo@kb.vlaanderen.be"
      },
      "foaf:name": "Data Vlaanderen",
      "foaf:homepage": {
        "@id": "https://data.vlaanderen.be"
      }
    },
    {
      "@id": "_:g47250426590000",
      "foaf:firstName": "Jens",
      "foaf:lastName": "Scheerlinck",
      "schema:affiliation": {
        "@id": "_:g47250426556760"
      },
      "@type": "foaf:person",
      "foaf:mbox": {
        "@id": "mailto:jens.scheerlinck@pwc.com"
      }
    },
    {
      "@id": "_:g47250423547960",
      "foaf:firstName": "Marc",
      "foaf:lastName": "Bruyland",
      "schema:affiliation": {
        "@id": "_:g47250421610060"
      },
      "@type": "foaf:person",
      "foaf:mbox": {
        "@id": "mailto:marc.bruyland@bosa.fgov.be"
      }
    },
    {
      "@id": "_:g47250427393020",
      "foaf:firstName": "Els",
      "foaf:lastName": "Podevyn",
      "schema:affiliation": {
        "@id": "_:g47250427608260"
      },
      "@type": "foaf:person",
      "foaf:mbox": {
        "@id": "mailto:els.podevyn@sint-niklaas.be"
      }
    },
    {
      "@id": "_:g47250429989920",
      "foaf:firstName": "Cornelis",
      "foaf:lastName": "Stal",
      "schema:affiliation": {
        "@id": "_:g47250429996520"
      },
      "@type": "foaf:person",
      "foaf:mbox": {
        "@id": "mailto:cornelis.stal@hogent.be"
      }
    },
    {
      "@id": "_:g47250430448460",
      "foaf:firstName": "Jan",
      "foaf:lastName": "De Wael",
      "schema:affiliation": {
        "@id": "_:g47250430465260"
      },
      "@type": "foaf:person",
      "foaf:mbox": {
        "@id": "mailto:jan.dewael@aalst.be"
      }
    },
    {
      "@id": "_:g47250427511400",
      "foaf:firstName": "Ellen",
      "foaf:lastName": "Debever",
      "schema:affiliation": {
        "@id": "_:g47250430336740"
      },
      "@type": "foaf:person",
      "foaf:mbox": {
        "@id": "mailto:ellen.debever@oostende.be"
      }
    },
    {
      "@id": "_:g47250428603400",
      "foaf:firstName": "Diedrik",
      "foaf:lastName": "Gaus",
      "schema:affiliation": {
        "@id": "_:g47250428455280"
      },
      "@type": "foaf:person",
      "foaf:mbox": {
        "@id": "mailto:Diedrik.gaus@stad.gent"
      }
    },
    {
      "@id": "_:g47250430640700",
      "foaf:firstName": "Pieter",
      "foaf:lastName": "Lauwereys",
      "schema:affiliation": {
        "@id": "_:g47250427138160"
      },
      "@type": "foaf:person",
      "foaf:mbox": {
        "@id": "mailto:pieter.lauwereys@aalst.be"
      }
    },
    {
      "@id": "_:g47250430119120",
      "foaf:firstName": "Peter",
      "foaf:lastName": "Van de Veire",
      "schema:affiliation": {
        "@id": "_:g47250430127380"
      },
      "@type": "foaf:person",
      "foaf:mbox": {
        "@id": "mailto:peter.vandeveire@evergem.be"
      }
    },
    {
      "@id": "_:g47250428133060",
      "foaf:firstName": "Floris",
      "foaf:lastName": "Van den Broeck",
      "schema:affiliation": {
        "@id": "_:g47250428357160"
      },
      "@type": "foaf:person",
      "foaf:mbox": {
        "@id": "mailto:floris.vandenbroeck@vlaamsbrabant.be"
      }
    },
    {
      "@id": "_:g47250427501260",
      "foaf:firstName": "Luc",
      "foaf:lastName": "Janssens",
      "schema:affiliation": {
        "@id": "_:g47250427431040"
      },
      "@type": "foaf:person",
      "foaf:mbox": {
        "@id": "mailto:luc.janssens@lier.be"
      }
    },
    {
      "@id": "_:g47250430065060",
      "foaf:firstName": "Reinhilde",
      "foaf:lastName": "Schepens",
      "schema:affiliation": {
        "@id": "_:g47250428158220"
      },
      "@type": "foaf:person",
      "foaf:mbox": {
        "@id": "mailto:reinhilde.schepens@wenz.be"
      }
    },
    {
      "@id": "_:g47250431015120",
      "foaf:firstName": "Tim",
      "foaf:lastName": "Baert",
      "schema:affiliation": {
        "@id": "_:g47250431027680"
      },
      "@type": "foaf:person",
      "foaf:mbox": {
        "@id": "mailto:tim.baert@ugent.be"
      }
    },
    {
      "@id": "_:g47250421610060",
      "foaf:name": "Federale Overheidsdienst Beleid en Ondersteuning"
    },
    {
      "@id": "_:g47250427138160",
      "foaf:name": "Stad Aalst"
    },
    {
      "@id": "_:g47250428158220",
      "foaf:name": "De Vlaamse Waterweg nv"
    },
    {
      "@id": "_:g47250426556760",
      "foaf:name": "PwC",
      "foaf:homepage": {
        "@id": "http://www.pwc.be"
      }
    },
    {
      "@id": "_:g47250429996520",
      "foaf:name": "Hogeschool Gent"
    },
    {
      "@id": "_:g47250431027680",
      "foaf:name": "Ugent"
    },
    {
      "@id": "https://data.vlaanderen.be/ns/openbaardomein/begraafplaats#Strooiweide",
      "rdfs:comment": {
        "@value": "Plaats, meestal grasperkje, op het kerkhof waar assen van overledenen uitgestrooid worden.",
        "@language": "nl"
      },
      "rdfs:isDefinedBy": {
        "@id": "https://data.vlaanderen.be/ns/openbaardomein/begraafplaats"
      },
      "@type": "owl:Class",
      "rdfs:label": {
        "@value": "Strooiweide",
        "@language": "nl"
      },
      "rdfs:subClassOf": {
        "@id": "https://data.vlaanderen.be/ns/openbaardomein/terreindeel#Terreindeel"
      }
    }
  ]
}